ml_extra/decorators/mlflow/exp_tracking.py
ml_extra/experiment_tracking/mlflow/experiments.py
ml_extra-0.2.0.dist-info/METADATA
ml_extra-0.2.0.dist-info/WHEEL
ml_extra-0.2.0.dist-info/entry_points.txt
ml_extra-0.2.0.dist-info/RECORD
