Metadata-Version: 2.3
Name: ml-extra
Version: 0.2.0
Summary: 
Author: Manuel Gil
Author-email: manuelgilsitio@gmail.com
Requires-Python: >=3.11,<4.0
Classifier: Programming Language :: Python :: 3
Classifier: Programming Language :: Python :: 3.11
Classifier: Programming Language :: Python :: 3.12
Classifier: Programming Language :: Python :: 3.13
